{"version":"tree-0.1","tree":{"id":"App","path":"","constructInfo":{"fqn":"aws-cdk-lib.App","version":"2.230.0"},"children":{"MyCdkProjectStack":{"id":"MyCdkProjectStack","path":"MyCdkProjectStack","constructInfo":{"fqn":"aws-cdk-lib.Stack","version":"2.230.0"},"children":{"MyFirstBucket":{"id":"MyFirstBucket","path":"MyCdkProjectStack/MyFirstBucket","constructInfo":{"fqn":"aws-cdk-lib.aws_s3.Bucket","version":"2.230.0","metadata":[]},"children":{"Resource":{"id":"Resource","path":"MyCdkProjectStack/MyFirstBucket/Resource","constructInfo":{"fqn":"aws-cdk-lib.aws_s3.CfnBucket","version":"2.230.0"},"attributes":{"aws:cdk:cloudformation:type":"AWS::S3::Bucket","aws:cdk:cloudformation:props":{"tags":[{"key":"aws-cdk:auto-delete-objects","value":"true"}],"versioningConfiguration":{"status":"Enabled"}}}},"Policy":{"id":"Policy","path":"MyCdkProjectStack/MyFirstBucket/Policy","constructInfo":{"fqn":"aws-cdk-lib.aws_s3.BucketPolicy","version":"2.230.0","metadata":[]},"children":{"Resource":{"id":"Resource","path":"MyCdkProjectStack/MyFirstBucket/Policy/Resource","constructInfo":{"fqn":"aws-cdk-lib.aws_s3.CfnBucketPolicy","version":"2.230.0"},"attributes":{"aws:cdk:cloudformation:type":"AWS::S3::BucketPolicy","aws:cdk:cloudformation:props":{"bucket":{"Ref":"MyFirstBucketB8884501"},"policyDocument":{"Statement":[{"Action":["s3:PutBucketPolicy","s3:GetBucket*","s3:List*","s3:DeleteObject*"],"Effect":"Allow","Principal":{"AWS":{"Fn::GetAtt":["CustomS3AutoDeleteObjectsCustomResourceProviderRole3B1BD092","Arn"]}},"Resource":[{"Fn::GetAtt":["MyFirstBucketB8884501","Arn"]},{"Fn::Join":["",[{"Fn::GetAtt":["MyFirstBucketB8884501","Arn"]},"/*"]]}]}],"Version":"2012-10-17"}}}}}},"AutoDeleteObjectsCustomResource":{"id":"AutoDeleteObjectsCustomResource","path":"MyCdkProjectStack/MyFirstBucket/AutoDeleteObjectsCustomResource","constructInfo":{"fqn":"aws-cdk-lib.CustomResource","version":"2.230.0","metadata":[]},"children":{"Default":{"id":"Default","path":"MyCdkProjectStack/MyFirstBucket/AutoDeleteObjectsCustomResource/Default","constructInfo":{"fqn":"aws-cdk-lib.CfnResource","version":"2.230.0"}}}},"Notifications":{"id":"Notifications","path":"MyCdkProjectStack/MyFirstBucket/Notifications","constructInfo":{"fqn":"constructs.Construct","version":"10.4.3"},"children":{"Resource":{"id":"Resource","path":"MyCdkProjectStack/MyFirstBucket/Notifications/Resource","constructInfo":{"fqn":"aws-cdk-lib.CfnResource","version":"2.230.0"}}}},"AllowBucketNotificationsToMyCdkProjectStackMyLambda6B7611B1":{"id":"AllowBucketNotificationsToMyCdkProjectStackMyLambda6B7611B1","path":"MyCdkProjectStack/MyFirstBucket/AllowBucketNotificationsToMyCdkProjectStackMyLambda6B7611B1","constructInfo":{"fqn":"aws-cdk-lib.aws_lambda.CfnPermission","version":"2.230.0"},"attributes":{"aws:cdk:cloudformation:type":"AWS::Lambda::Permission","aws:cdk:cloudformation:props":{"action":"lambda:InvokeFunction","functionName":{"Fn::GetAtt":["MyLambdaCCE802FB","Arn"]},"principal":"s3.amazonaws.com","sourceAccount":{"Ref":"AWS::AccountId"},"sourceArn":{"Fn::GetAtt":["MyFirstBucketB8884501","Arn"]}}}}}},"Custom::S3AutoDeleteObjectsCustomResourceProvider":{"id":"Custom::S3AutoDeleteObjectsCustomResourceProvider","path":"MyCdkProjectStack/Custom::S3AutoDeleteObjectsCustomResourceProvider","constructInfo":{"fqn":"aws-cdk-lib.CustomResourceProviderBase","version":"2.230.0"},"children":{"Staging":{"id":"Staging","path":"MyCdkProjectStack/Custom::S3AutoDeleteObjectsCustomResourceProvider/Staging","constructInfo":{"fqn":"aws-cdk-lib.AssetStaging","version":"2.230.0"}},"Role":{"id":"Role","path":"MyCdkProjectStack/Custom::S3AutoDeleteObjectsCustomResourceProvider/Role","constructInfo":{"fqn":"aws-cdk-lib.CfnResource","version":"2.230.0"}},"Handler":{"id":"Handler","path":"MyCdkProjectStack/Custom::S3AutoDeleteObjectsCustomResourceProvider/Handler","constructInfo":{"fqn":"aws-cdk-lib.CfnResource","version":"2.230.0"}}}},"MyTable":{"id":"MyTable","path":"MyCdkProjectStack/MyTable","constructInfo":{"fqn":"aws-cdk-lib.aws_dynamodb.Table","version":"2.230.0","metadata":[]},"children":{"Resource":{"id":"Resource","path":"MyCdkProjectStack/MyTable/Resource","constructInfo":{"fqn":"aws-cdk-lib.aws_dynamodb.CfnTable","version":"2.230.0"},"attributes":{"aws:cdk:cloudformation:type":"AWS::DynamoDB::Table","aws:cdk:cloudformation:props":{"attributeDefinitions":[{"attributeName":"id","attributeType":"S"}],"billingMode":"PAY_PER_REQUEST","keySchema":[{"attributeName":"id","keyType":"HASH"}],"tableName":"MyTable"}}},"ScalingRole":{"id":"ScalingRole","path":"MyCdkProjectStack/MyTable/ScalingRole","constructInfo":{"fqn":"aws-cdk-lib.Resource","version":"2.230.0","metadata":[]}}}},"MyLambda":{"id":"MyLambda","path":"MyCdkProjectStack/MyLambda","constructInfo":{"fqn":"aws-cdk-lib.aws_lambda.Function","version":"2.230.0","metadata":[]},"children":{"ServiceRole":{"id":"ServiceRole","path":"MyCdkProjectStack/MyLambda/ServiceRole","constructInfo":{"fqn":"aws-cdk-lib.aws_iam.Role","version":"2.230.0","metadata":[]},"children":{"ImportServiceRole":{"id":"ImportServiceRole","path":"MyCdkProjectStack/MyLambda/ServiceRole/ImportServiceRole","constructInfo":{"fqn":"aws-cdk-lib.Resource","version":"2.230.0","metadata":[]}},"Resource":{"id":"Resource","path":"MyCdkProjectStack/MyLambda/ServiceRole/Resource","constructInfo":{"fqn":"aws-cdk-lib.aws_iam.CfnRole","version":"2.230.0"},"attributes":{"aws:cdk:cloudformation:type":"AWS::IAM::Role","aws:cdk:cloudformation:props":{"assumeRolePolicyDocument":{"Statement":[{"Action":"sts:AssumeRole","Effect":"Allow","Principal":{"Service":"lambda.amazonaws.com"}}],"Version":"2012-10-17"},"managedPolicyArns":[{"Fn::Join":["",["arn:",{"Ref":"AWS::Partition"},":iam::aws:policy/service-role/AWSLambdaBasicExecutionRole"]]}]}}},"DefaultPolicy":{"id":"DefaultPolicy","path":"MyCdkProjectStack/MyLambda/ServiceRole/DefaultPolicy","constructInfo":{"fqn":"aws-cdk-lib.aws_iam.Policy","version":"2.230.0","metadata":[]},"children":{"Resource":{"id":"Resource","path":"MyCdkProjectStack/MyLambda/ServiceRole/DefaultPolicy/Resource","constructInfo":{"fqn":"aws-cdk-lib.aws_iam.CfnPolicy","version":"2.230.0"},"attributes":{"aws:cdk:cloudformation:type":"AWS::IAM::Policy","aws:cdk:cloudformation:props":{"policyDocument":{"Statement":[{"Action":["s3:GetObject*","s3:GetBucket*","s3:List*","s3:DeleteObject*","s3:PutObject","s3:PutObjectLegalHold","s3:PutObjectRetention","s3:PutObjectTagging","s3:PutObjectVersionTagging","s3:Abort*"],"Effect":"Allow","Resource":[{"Fn::GetAtt":["MyFirstBucketB8884501","Arn"]},{"Fn::Join":["",[{"Fn::GetAtt":["MyFirstBucketB8884501","Arn"]},"/*"]]}]},{"Action":["dynamodb:BatchGetItem","dynamodb:GetRecords","dynamodb:GetShardIterator","dynamodb:Query","dynamodb:GetItem","dynamodb:Scan","dynamodb:ConditionCheckItem","dynamodb:BatchWriteItem","dynamodb:PutItem","dynamodb:UpdateItem","dynamodb:DeleteItem","dynamodb:DescribeTable"],"Effect":"Allow","Resource":{"Fn::GetAtt":["MyTable794EDED1","Arn"]}}],"Version":"2012-10-17"},"policyName":"MyLambdaServiceRoleDefaultPolicy5BBC6F68","roles":[{"Ref":"MyLambdaServiceRole4539ECB6"}]}}}}}}},"Code":{"id":"Code","path":"MyCdkProjectStack/MyLambda/Code","constructInfo":{"fqn":"aws-cdk-lib.aws_s3_assets.Asset","version":"2.230.0"},"children":{"Stage":{"id":"Stage","path":"MyCdkProjectStack/MyLambda/Code/Stage","constructInfo":{"fqn":"aws-cdk-lib.AssetStaging","version":"2.230.0"}},"AssetBucket":{"id":"AssetBucket","path":"MyCdkProjectStack/MyLambda/Code/AssetBucket","constructInfo":{"fqn":"aws-cdk-lib.aws_s3.BucketBase","version":"2.230.0","metadata":[]}}}},"Resource":{"id":"Resource","path":"MyCdkProjectStack/MyLambda/Resource","constructInfo":{"fqn":"aws-cdk-lib.aws_lambda.CfnFunction","version":"2.230.0"},"attributes":{"aws:cdk:cloudformation:type":"AWS::Lambda::Function","aws:cdk:cloudformation:props":{"code":{"s3Bucket":{"Fn::Sub":"cdk-hnb659fds-assets-${AWS::AccountId}-${AWS::Region}"},"s3Key":"afacbe3aee29aae4603c9f19084d7d20bdddce296c537a782e4b375d7d3f7fc2.zip"},"environment":{"variables":{"BUCKET_NAME":{"Ref":"MyFirstBucketB8884501"},"TABLE_NAME":{"Ref":"MyTable794EDED1"}}},"handler":"index.handler","memorySize":128,"role":{"Fn::GetAtt":["MyLambdaServiceRole4539ECB6","Arn"]},"runtime":"nodejs18.x","timeout":10}}}}},"BucketNotificationsHandler050a0587b7544547bf325f094a3db834":{"id":"BucketNotificationsHandler050a0587b7544547bf325f094a3db834","path":"MyCdkProjectStack/BucketNotificationsHandler050a0587b7544547bf325f094a3db834","constructInfo":{"fqn":"constructs.Construct","version":"10.4.3"},"children":{"Role":{"id":"Role","path":"MyCdkProjectStack/BucketNotificationsHandler050a0587b7544547bf325f094a3db834/Role","constructInfo":{"fqn":"aws-cdk-lib.aws_iam.Role","version":"2.230.0","metadata":[]},"children":{"ImportRole":{"id":"ImportRole","path":"MyCdkProjectStack/BucketNotificationsHandler050a0587b7544547bf325f094a3db834/Role/ImportRole","constructInfo":{"fqn":"aws-cdk-lib.Resource","version":"2.230.0","metadata":[]}},"Resource":{"id":"Resource","path":"MyCdkProjectStack/BucketNotificationsHandler050a0587b7544547bf325f094a3db834/Role/Resource","constructInfo":{"fqn":"aws-cdk-lib.aws_iam.CfnRole","version":"2.230.0"},"attributes":{"aws:cdk:cloudformation:type":"AWS::IAM::Role","aws:cdk:cloudformation:props":{"assumeRolePolicyDocument":{"Statement":[{"Action":"sts:AssumeRole","Effect":"Allow","Principal":{"Service":"lambda.amazonaws.com"}}],"Version":"2012-10-17"},"managedPolicyArns":[{"Fn::Join":["",["arn:",{"Ref":"AWS::Partition"},":iam::aws:policy/service-role/AWSLambdaBasicExecutionRole"]]}]}}},"DefaultPolicy":{"id":"DefaultPolicy","path":"MyCdkProjectStack/BucketNotificationsHandler050a0587b7544547bf325f094a3db834/Role/DefaultPolicy","constructInfo":{"fqn":"aws-cdk-lib.aws_iam.Policy","version":"2.230.0","metadata":[]},"children":{"Resource":{"id":"Resource","path":"MyCdkProjectStack/BucketNotificationsHandler050a0587b7544547bf325f094a3db834/Role/DefaultPolicy/Resource","constructInfo":{"fqn":"aws-cdk-lib.aws_iam.CfnPolicy","version":"2.230.0"},"attributes":{"aws:cdk:cloudformation:type":"AWS::IAM::Policy","aws:cdk:cloudformation:props":{"policyDocument":{"Statement":[{"Action":"s3:PutBucketNotification","Effect":"Allow","Resource":{"Fn::GetAtt":["MyFirstBucketB8884501","Arn"]}}],"Version":"2012-10-17"},"policyName":"BucketNotificationsHandler050a0587b7544547bf325f094a3db834RoleDefaultPolicy2CF63D36","roles":[{"Ref":"BucketNotificationsHandler050a0587b7544547bf325f094a3db834RoleB6FB88EC"}]}}}}}}},"Resource":{"id":"Resource","path":"MyCdkProjectStack/BucketNotificationsHandler050a0587b7544547bf325f094a3db834/Resource","constructInfo":{"fqn":"aws-cdk-lib.CfnResource","version":"2.230.0"}}}},"BucketNameOutput":{"id":"BucketNameOutput","path":"MyCdkProjectStack/BucketNameOutput","constructInfo":{"fqn":"aws-cdk-lib.CfnOutput","version":"2.230.0"}},"TableNameOutput":{"id":"TableNameOutput","path":"MyCdkProjectStack/TableNameOutput","constructInfo":{"fqn":"aws-cdk-lib.CfnOutput","version":"2.230.0"}},"LambdaNameOutput":{"id":"LambdaNameOutput","path":"MyCdkProjectStack/LambdaNameOutput","constructInfo":{"fqn":"aws-cdk-lib.CfnOutput","version":"2.230.0"}},"CDKMetadata":{"id":"CDKMetadata","path":"MyCdkProjectStack/CDKMetadata","constructInfo":{"fqn":"constructs.Construct","version":"10.4.3"},"children":{"Default":{"id":"Default","path":"MyCdkProjectStack/CDKMetadata/Default","constructInfo":{"fqn":"aws-cdk-lib.CfnResource","version":"2.230.0"}},"Condition":{"id":"Condition","path":"MyCdkProjectStack/CDKMetadata/Condition","constructInfo":{"fqn":"aws-cdk-lib.CfnCondition","version":"2.230.0"}}}},"BootstrapVersion":{"id":"BootstrapVersion","path":"MyCdkProjectStack/BootstrapVersion","constructInfo":{"fqn":"aws-cdk-lib.CfnParameter","version":"2.230.0"}},"CheckBootstrapVersion":{"id":"CheckBootstrapVersion","path":"MyCdkProjectStack/CheckBootstrapVersion","constructInfo":{"fqn":"aws-cdk-lib.CfnRule","version":"2.230.0"}}}},"Tree":{"id":"Tree","path":"Tree","constructInfo":{"fqn":"constructs.Construct","version":"10.4.3"}}}}}